ezcoding/__init__.py
ezcoding/const.py
ezcoding/generator.py
ezcoding/task.py
ezcoding/template.py
ezcoding/utils.py
ezcoding/generators/__init__.py
ezcoding/generators/author_generator.py
ezcoding/generators/date_string_generator.py
ezcoding/generators/header_filename_generator.py
ezcoding/generators/header_macro_generator.py
ezcoding/generators/uuid_string_generator.py
ezcoding/ui/__init__.py
ezcoding/ui/application.py
ezcoding/ui/editor.py
ezcoding_cli/__init__.py
ezcoding_cli/command.py
ezcoding_cli/command_manager.py
ezcoding_cli/main.py
ezcoding_cli/utils.py
ezcoding_cli/commands/__init__.py
ezcoding_cli/commands/cmd_create.py
ezcoding_cli/commands/cmd_help.py
ezcoding_cli/commands/cmd_list_templates.py
ezcoding-0.2.4.dist-info/LICENSE
ezcoding-0.2.4.dist-info/METADATA
ezcoding-0.2.4.dist-info/WHEEL
ezcoding-0.2.4.dist-info/entry_points.txt
ezcoding-0.2.4.dist-info/top_level.txt
ezcoding-0.2.4.dist-info/RECORD
