Metadata-Version: 2.1
Name: ezcoding
Version: 0.2.4
Summary: Easy coding
Home-page: https://gitee.com/zhuuuoyue/ezcoding
Author: zhuoy
Author-email: zhuoyue_cn@yeah.net
License: MIT
License-File: LICENSE
